ttydal/__init__.py
ttydal/api_logger.py
ttydal/app.py
ttydal/components/__init__.py
ttydal/components/albums_list.py
ttydal/components/cache_modal.py
ttydal/components/cover_art_item.py
ttydal/components/login_modal.py
ttydal/components/player_bar.py
ttydal/components/search_modal.py
ttydal/components/tracks_list.py
ttydal/config.py
ttydal/credentials.py
ttydal/exceptions.py
ttydal/image_cache.py
ttydal/logger.py
ttydal/pages/__init__.py
ttydal/pages/config_page.py
ttydal/pages/player_page.py
ttydal/player.py
ttydal/services/__init__.py
ttydal/services/playback_service.py
ttydal/services/tracks_cache.py
ttydal/tidal_client.py
ttydal-1.2.0.dist-info/WHEEL
ttydal-1.2.0.dist-info/entry_points.txt
ttydal-1.2.0.dist-info/METADATA
ttydal-1.2.0.dist-info/RECORD
