Metadata-Version: 2.4
Name: ttydal
Version: 1.2.0
Summary: Tidal in your terminal!
Author: Bouteiller [a2n] Alan
Author-email: Bouteiller [a2n] Alan <a2n.dev@pm.me>
License-Expression: AGPL-3.0-or-later
Requires-Dist: appdirs>=1.4.4
Requires-Dist: cachetools>=6.2.4
Requires-Dist: fuzzysearch>=0.8.1
Requires-Dist: keyring>=25.7.0
Requires-Dist: mpv>=1.0.8
Requires-Dist: platformdirs>=4.5.1
Requires-Dist: pydantic>=2.12.5
Requires-Dist: pyperclip>=1.9.0
Requires-Dist: rich>=14.2.0
Requires-Dist: textual>=7.0.1
Requires-Dist: textual-dev>=1.8.0
Requires-Dist: textual-image>=0.8.5
Requires-Dist: tidalapi>=0.8.10
Requires-Python: >=3.13
Project-URL: Homepage, https://github.com/results-may-vary-org/ttydal
Project-URL: Issues, https://github.com/results-may-vary-org/ttydal/issues
Project-URL: Repository, https://github.com/results-may-vary-org/ttydal
